bootrom-verif/cov/final_vcode/annotated/boot_rom.sv
//      // verilator_coverage annotation
        module boot_rom #(
          parameter int ADDR_WIDTH = 10,  // 1024 words = 4 KB
          parameter     INIT_FILE  = "boot.mem"
        )(
 021524   input  logic              clk_i,
 006972   input  logic [ADDR_WIDTH-1:0] addr_i,
~005388   output logic [31:0]       data_o
        );
        
          logic [31:0] mem [0:2**ADDR_WIDTH-1];
        
%000003   initial begin
%000003     $readmemh(INIT_FILE, mem);
          end
        
 021524   always_ff @(posedge clk_i) begin
 021524     data_o <= mem[addr_i];
          end
        
        endmodule

bootrom-verif/waves/TC_003_bootrom_random_access_test.vcd
$version Generated by VerilatedVcd $end
$timescale 1ps $end
 $scope module TOP $end
  $var wire 1 " clk_i $end
  $var wire 10 # addr_i [9:0] $end
  $var wire 32 $ data_o [31:0] $end
  $scope module boot_rom $end
   $var wire 32 % ADDR_WIDTH [31:0] $end
   $var wire 64 & INIT_FILE [63:0] $end
   $var wire 1 " clk_i $end
   $var wire 10 # addr_i [9:0] $end
   $var wire 32 $ data_o [31:0] $end
  $upscope $end
 $upscope $end
$enddefinitions $end


#0
0"
b0000000001 #
b00000000000000000000000000000000 $
b00000000000000000000000000001010 %
b0110001001101111011011110111010000101110011011010110010101101101 &
#5
1"
b00000000000000000000000000010000 $
#10
0"
b1111111110 #
#15
1"
b00000000000000000000000000000000 $
#20
0"
b1010101011 #
#25
1"
#30
0"
b1010101110 #
#35
1"
#40
0"
b0000000000 #
#45
1"
b00000000000000000000000010110111 $
#50
0"
b0001000111 #
#55
1"
b00000000000000000000000000000000 $
#60
0"
b0001000000 #
#65
1"
b00000000000000000000000000000001 $
#70
0"
b1110111111 #
#75
1"
b00000000000000000000000000000000 $
#80
0"
b1011101010 #
#85
1"
#90
0"
b1110111010 #
#95
1"
#100
0"
b0000000000 #
#105
1"
b00000000000000000000000010110111 $
#110
0"
b0110010101 #
#115
1"
b00000000000000000000000000000000 $
#120
0"
b0000000100 #
#125
1"
b00000000000000000000000010010011 $
#130
0"
b1111111011 #
#135
1"
b00000000000000000000000000000000 $
#140
0"
b1010101110 #
#145
1"
#150
0"
b1010111011 #
#155
1"
#160
0"
b0000000000 #
#165
1"
b00000000000000000000000010110111 $
#170
0"
b1111101101 #
#175
1"
b00000000000000000000000000000000 $
#180
0"
b0100000000 #
#185
1"
#190
0"
b1011111111 #
#195
1"
#200
0"
b1110101010 #
#205
1"
#210
0"
b1011101010 #
#215
1"
#220
0"
b0000000000 #
#225
1"
b00000000000000000000000010110111 $
#230
0"
b1100111011 #
#235
1"
b00000000000000000000000000000000 $
#240
0"
b0000010000 #
#245
1"
b00000000000000000000000010110111 $
#250
0"
b1111101111 #
#255
1"
b00000000000000000000000000000000 $
#260
0"
b1010111010 #
#265
1"
#270
0"
b1011101110 #
#275
1"
#280
0"
b0000000000 #
#285
1"
b00000000000000000000000010110111 $
#290
0"
b1001100001 #
#295
1"
b00000000000000000000000000000000 $
#300
0"
b0000000001 #
#305
1"
b00000000000000000000000000010000 $
#310
0"
b1111111110 #
#315
1"
b00000000000000000000000000000000 $
#320
0"
b1010101011 #
#325
1"
#330
0"
b1010101110 #
#335
1"
#340
0"
b0000000000 #
#345
1"
b00000000000000000000000010110111 $
#350
0"
b0111010000 #
#355
1"
b00000000000000000000000000000000 $
#360
0"
b0001000000 #
#365
1"
b00000000000000000000000000000001 $
#370
0"
b1110111111 #
#375
1"
b00000000000000000000000000000000 $
#380
0"
b1011101010 #
#385
1"
#390
0"
b1110111010 #
#395
1"
#400
0"
b0000000000 #
#405
1"
b00000000000000000000000010110111 $
#410
0"
b0111000001 #
#415
1"
b00000000000000000000000000000000 $
#420
0"
b0000000100 #
#425
1"
b00000000000000000000000010010011 $
#430
0"
b1111111011 #
#435
1"
b00000000000000000000000000000000 $
#440
0"
b1010101110 #
#445
1"
#450
0"
b1010111011 #
#455
1"
#460
0"
b0000000000 #
#465
1"
b00000000000000000000000010110111 $
#470
0"
b0011001110 #
#475
1"
b00000000000000000000000000000000 $
#480
0"
b0100000000 #
#485
1"
#490
0"
b1011111111 #
#495
1"
#500
0"
b1110101010 #
#505
1"
#510
0"
b1011101010 #
#515
1"
#520
0"
b0000000000 #
#525
1"
b00000000000000000000000010110111 $
#530
0"
b0110011000 #
#535
1"
b00000000000000000000000000000000 $
#540
0"
b0000010000 #
#545
1"
b00000000000000000000000010110111 $
#550
0"
b1111101111 #
#555
1"
b00000000000000000000000000000000 $
#560
0"
b1010111010 #
#565
1"
#570
0"
b1011101110 #
#575
1"
#580
0"
b0000000000 #
#585
1"
b00000000000000000000000010110111 $
#590
0"
b1111111000 #
#595
1"
b00000000000000000000000000000000 $
#600
0"
b0000000001 #
#605
1"
b00000000000000000000000000010000 $
#610
0"
b1111111110 #
#615
1"
b00000000000000000000000000000000 $
#620
0"
b1010101011 #
#625
1"
#630
0"
b1010101110 #
#635
1"
#640
0"
b0000000000 #
#645
1"
b00000000000000000000000010110111 $
#650
0"
b0000011011 #
#655
1"
b00000000000000000000000001000100 $
#660
0"
b0001000000 #
#665
1"
b00000000000000000000000000000001 $
#670
0"
b1110111111 #
#675
1"
b00000000000000000000000000000000 $
#680
0"
b1011101010 #
#685
1"
#690
0"
b1110111010 #
#695
1"
#700
0"
b0000000000 #
#705
1"
b00000000000000000000000010110111 $
#710
0"
b1101000001 #
#715
1"
b00000000000000000000000000000000 $
#720
0"
b0000000100 #
#725
1"
b00000000000000000000000010010011 $
#730
0"
b1111111011 #
#735
1"
b00000000000000000000000000000000 $
#740
0"
b1010101110 #
#745
1"
#750
0"
b1010111011 #
#755
1"
#760
0"
b0000000000 #
#765
1"
b00000000000000000000000010110111 $
#770
0"
b0000011001 #
#775
1"
b00000000000000000000000001000010 $
#780
0"
b0100000000 #
#785
1"
b00000000000000000000000000000000 $
#790
0"
b1011111111 #
#795
1"
#800
0"
b1110101010 #
#805
1"
#810
0"
b1011101010 #
#815
1"
#820
0"
b0000000000 #
#825
1"
b00000000000000000000000010110111 $
#830
0"
b0100010101 #
#835
1"
b00000000000000000000000000000000 $
#840
0"
b0000010000 #
#845
1"
b00000000000000000000000010110111 $
#850
0"
b1111101111 #
#855
1"
b00000000000000000000000000000000 $
#860
0"
b1010111010 #
#865
1"
#870
0"
b1011101110 #
#875
1"
#880
0"
b0000000000 #
#885
1"
b00000000000000000000000010110111 $
#890
0"
b0110001110 #
#895
1"
b00000000000000000000000000000000 $
#900
0"
b0000000001 #
#905
1"
b00000000000000000000000000010000 $
#910
0"
b1111111110 #
#915
1"
b00000000000000000000000000000000 $
#920
0"
b1010101011 #
#925
1"
#930
0"
b1010101110 #
#935
1"
#940
0"
b0000000000 #
#945
1"
b00000000000000000000000010110111 $
#950
0"
b1011010101 #
#955
1"
b00000000000000000000000000000000 $
#960
0"
b0001000000 #
#965
1"
b00000000000000000000000000000001 $
#970
0"
b1110111111 #
#975
1"
b00000000000000000000000000000000 $
#980
0"
b1011101010 #
#985
1"
#990
0"
b1110111010 #
#995
1"
#1000
0"
b0000000000 #
#1005
1"
b00000000000000000000000010110111 $
#1010
0"
b0111010010 #
#1015
1"
b00000000000000000000000000000000 $
#1020
0"
b0000000100 #
#1025
1"
b00000000000000000000000010010011 $
#1030
0"
b1111111011 #
#1035
1"
b00000000000000000000000000000000 $
#1040
0"
b1010101110 #
#1045
1"
#1050
0"
b1010111011 #
#1055
1"
#1060
0"
b0000000000 #
#1065
1"
b00000000000000000000000010110111 $
#1070
0"
b1111000000 #
#1075
1"
b00000000000000000000000000000000 $
#1080
0"
b0100000000 #
#1085
1"
#1090
0"
b1011111111 #
#1095
1"
#1100
0"
b1110101010 #
#1105
1"
#1110
0"
b1011101010 #
#1115
1"
#1120
0"
b0000000000 #
#1125
1"
b00000000000000000000000010110111 $
#1130
0"
b1010001001 #
#1135
1"
b00000000000000000000000000000000 $
#1140
0"
b0000010000 #
#1145
1"
b00000000000000000000000010110111 $
#1150
0"
b1111101111 #
#1155
1"
b00000000000000000000000000000000 $
#1160
0"
b1010111010 #
#1165
1"
#1170
0"
b1011101110 #
#1175
1"
#1180
0"
b0000000000 #
#1185
1"
b00000000000000000000000010110111 $
#1190
0"
b1010111000 #
#1195
1"
b00000000000000000000000000000000 $
#1200
0"
b0000000001 #
#1205
1"
b00000000000000000000000000010000 $
#1210
0"
b1111111110 #
#1215
1"
b00000000000000000000000000000000 $
#1220
0"
b1010101011 #
#1225
1"
#1230
0"
b1010101110 #
#1235
1"
#1240
0"
b0000000000 #
#1245
1"
b00000000000000000000000010110111 $
#1250
0"
b0111011001 #
#1255
1"
b00000000000000000000000000000000 $
#1260
0"
b0001000000 #
#1265
1"
b00000000000000000000000000000001 $
#1270
0"
b1110111111 #
#1275
1"
b00000000000000000000000000000000 $
#1280
0"
b1011101010 #
#1285
1"
#1290
0"
b1110111010 #
#1295
1"
#1300
0"
b0000000000 #
#1305
1"
b00000000000000000000000010110111 $
#1310
0"
b0110100011 #
#1315
1"
b00000000000000000000000000000000 $
#1320
0"
b0000000100 #
#1325
1"
b00000000000000000000000010010011 $
#1330
0"
b1111111011 #
#1335
1"
b00000000000000000000000000000000 $
#1340
0"
b1010101110 #
#1345
1"
#1350
0"
b1010111011 #
#1355
1"
#1360
0"
b0000000000 #
#1365
1"
b00000000000000000000000010110111 $
#1370
0"
b1100101100 #
#1375
1"
b00000000000000000000000000000000 $
#1380
0"
b0100000000 #
#1385
1"
#1390
0"
b1011111111 #
#1395
1"
#1400
0"
b1110101010 #
#1405
1"
#1410
0"
b1011101010 #
#1415
1"
#1420
0"
b0000000000 #
#1425
1"
b00000000000000000000000010110111 $
#1430
0"
b0000111110 #
#1435
1"
b00000000000000000000000000010000 $
#1440
0"
b0000010000 #
#1445
1"
b00000000000000000000000010110111 $
#1450
0"
b1111101111 #
#1455
1"
b00000000000000000000000000000000 $
#1460
0"
b1010111010 #
#1465
1"
#1470
0"
b1011101110 #
#1475
1"
#1480
0"
b0000000000 #
#1485
1"
b00000000000000000000000010110111 $
#1490
0"
b1011001011 #
#1495
1"
b00000000000000000000000000000000 $
#1500
0"
b0000000001 #
#1505
1"
b00000000000000000000000000010000 $
#1510
0"
b1111111110 #
#1515
1"
b00000000000000000000000000000000 $
#1520
0"
b1010101011 #
#1525
1"
#1530
0"
b1010101110 #
#1535
1"
#1540
0"
b0000000000 #
#1545
1"
b00000000000000000000000010110111 $
#1550
0"
b0100001011 #
#1555
1"
b00000000000000000000000000000000 $
#1560
0"
b0001000000 #
#1565
1"
b00000000000000000000000000000001 $
#1570
0"
b1110111111 #
#1575
1"
b00000000000000000000000000000000 $
#1580
0"
b1011101010 #
#1585
1"
#1590
0"
b1110111010 #
#1595
1"
#1600
0"
b0000000000 #
#1605
1"
b00000000000000000000000010110111 $
#1610
0"
b1011100011 #
#1615
1"
b00000000000000000000000000000000 $
#1620
0"
b0000000100 #
#1625
1"
b00000000000000000000000010010011 $
#1630
0"
b1111111011 #
#1635
1"
b00000000000000000000000000000000 $
#1640
0"
b1010101110 #
#1645
1"
#1650
0"
b1010111011 #
#1655
1"
#1660
0"
b0000000000 #
#1665
1"
b00000000000000000000000010110111 $
#1670
0"
b0001010110 #
#1675
1"
b00000000000000000000000000000000 $
#1680
0"
b0100000000 #
#1685
1"
#1690
0"
b1011111111 #
#1695
1"
#1700
0"
b1110101010 #
#1705
1"
#1710
0"
b1011101010 #
#1715
1"
#1720
0"
b0000000000 #
#1725
1"
b00000000000000000000000010110111 $
#1730
0"
b1110000001 #
#1735
1"
b00000000000000000000000000000000 $
#1740
0"
b0000010000 #
#1745
1"
b00000000000000000000000010110111 $
#1750
0"
b1111101111 #
#1755
1"
b00000000000000000000000000000000 $
#1760
0"
b1010111010 #
#1765
1"
#1770
0"
b1011101110 #
#1775
1"
#1780
0"
b0000000000 #
#1785
1"
b00000000000000000000000010110111 $
#1790
0"
b1101000011 #
#1795
1"
b00000000000000000000000000000000 $
#1800
0"
b0000000001 #
#1805
1"
b00000000000000000000000000010000 $
#1810
0"
b1111111110 #
#1815
1"
b00000000000000000000000000000000 $
#1820
0"
b1010101011 #
#1825
1"
#1830
0"
b1010101110 #
#1835
1"
#1840
0"
b0000000000 #
#1845
1"
b00000000000000000000000010110111 $
#1850
0"
b1010001101 #
#1855
1"
b00000000000000000000000000000000 $
#1860
0"
b0001000000 #
#1865
1"
b00000000000000000000000000000001 $
#1870
0"
b1110111111 #
#1875
1"
b00000000000000000000000000000000 $
#1880
0"
b1011101010 #
#1885
1"
#1890
0"
b1110111010 #
#1895
1"
#1900
0"
b0000000000 #
#1905
1"
b00000000000000000000000010110111 $
#1910
0"
b1111001000 #
#1915
1"
b00000000000000000000000000000000 $
#1920
0"
b0000000100 #
#1925
1"
b00000000000000000000000010010011 $
#1930
0"
b1111111011 #
#1935
1"
b00000000000000000000000000000000 $
#1940
0"
b1010101110 #
#1945
1"
#1950
0"
b1010111011 #
#1955
1"
#1960
0"
b0000000000 #
#1965
1"
b00000000000000000000000010110111 $
#1970
0"
b0011011001 #
#1975
1"
b00000000000000000000000000000000 $
#1980
0"
b0100000000 #
#1985
1"
#1990
0"
b1011111111 #
#1995
1"
#2000
0"
b1110101010 #
#2005
1"
#2010
0"
b1011101010 #
#2015
1"
#2020
0"
b0000000000 #
#2025
1"
b00000000000000000000000010110111 $
#2030
0"
b1001111011 #
#2035
1"
b00000000000000000000000000000000 $
#2040
0"
b0000010000 #
#2045
1"
b00000000000000000000000010110111 $
#2050
0"
b1111101111 #
#2055
1"
b00000000000000000000000000000000 $
#2060
0"
b1010111010 #
#2065
1"
#2070
0"
b1011101110 #
#2075
1"
#2080
0"
b0000000000 #
#2085
1"
b00000000000000000000000010110111 $
#2090
0"
b1100000011 #
#2095
1"
b00000000000000000000000000000000 $
#2100
0"
b0000000001 #
#2105
1"
b00000000000000000000000000010000 $
#2110
0"
b1111111110 #
#2115
1"
b00000000000000000000000000000000 $
#2120
0"
b1010101011 #
#2125
1"
#2130
0"
b1010101110 #
#2135
1"
#2140
0"
b0000000000 #
#2145
1"
b00000000000000000000000010110111 $
#2150
0"
b1100111010 #
#2155
1"
b00000000000000000000000000000000 $
#2160
0"
b0001000000 #
#2165
1"
b00000000000000000000000000000001 $
#2170
0"
b1110111111 #
#2175
1"
b00000000000000000000000000000000 $
#2180
0"
b1011101010 #
#2185
1"
#2190
0"
b1110111010 #
#2195
1"
#2200
0"
b0000000000 #
#2205
1"
b00000000000000000000000010110111 $
#2210
0"
b0001001011 #
#2215
1"
b00000000000000000000000000000000 $
#2220
0"
b0000000100 #
#2225
1"
b00000000000000000000000010010011 $
#2230
0"
b1111111011 #
#2235
1"
b00000000000000000000000000000000 $
#2240
0"
b1010101110 #
#2245
1"
#2250
0"
b1010111011 #
#2255
1"
#2260
0"
b0000000000 #
#2265
1"
b00000000000000000000000010110111 $
#2270
0"
b0011000100 #
#2275
1"
b00000000000000000000000000000000 $
#2280
0"
b0100000000 #
#2285
1"
#2290
0"
b1011111111 #
#2295
1"
#2300
0"
b1110101010 #
#2305
1"
#2310
0"
b1011101010 #
#2315
1"
#2320
0"
b0000000000 #
#2325
1"
b00000000000000000000000010110111 $
#2330
0"
b0000001001 #
#2335
1"
b00000000000000000000000000100001 $
#2340
0"
b0000010000 #
#2345
1"
b00000000000000000000000010110111 $
#2350
0"
b1111101111 #
#2355
1"
b00000000000000000000000000000000 $
#2360
0"
b1010111010 #
#2365
1"
#2370
0"
b1011101110 #
#2375
1"
#2380
0"
b0000000000 #
#2385
1"
b00000000000000000000000010110111 $
#2390
0"
b0111100011 #
#2395
1"
b00000000000000000000000000000000 $
#2400
0"
b0000000001 #
#2405
1"
b00000000000000000000000000010000 $
#2410
0"
b1111111110 #
#2415
1"
b00000000000000000000000000000000 $
#2420
0"
b1010101011 #
#2425
1"
#2430
0"
b1010101110 #
#2435
1"
#2440
0"
b0000000000 #
#2445
1"
b00000000000000000000000010110111 $
#2450
0"
b0010111100 #
#2455
1"
b00000000000000000000000000000000 $
#2460
0"
b0001000000 #
#2465
1"
b00000000000000000000000000000001 $
#2470
0"
b1110111111 #
#2475
1"
b00000000000000000000000000000000 $
#2480
0"
b1011101010 #
#2485
1"
#2490
0"
b1110111010 #
#2495
1"
#2500
0"
b0000000000 #
#2505
1"
b00000000000000000000000010110111 $
#2510
0"
b0000100100 #
#2515
1"
b00000000000000000000000000110011 $
#2520
0"
b0000000100 #
#2525
1"
b00000000000000000000000010010011 $
#2530
0"
b1111111011 #
#2535
1"
b00000000000000000000000000000000 $
#2540
0"
b1010101110 #
#2545
1"
#2550
0"
b1010111011 #
#2555
1"
#2560
0"
b0000000000 #
#2565
1"
b00000000000000000000000010110111 $
#2570
0"
b0100100100 #
#2575
1"
b00000000000000000000000000000000 $
#2580
0"
b0100000000 #
#2585
1"
#2590
0"
b1011111111 #
#2595
1"
#2600
0"
b1110101010 #
#2605
1"
#2610
0"
b1011101010 #
#2615
1"
#2620
0"
b0000000000 #
#2625
1"
b00000000000000000000000010110111 $
#2630
0"
b0011010101 #
#2635
1"
b00000000000000000000000000000000 $
#2640
0"
b0000010000 #
#2645
1"
b00000000000000000000000010110111 $
#2650
0"
b1111101111 #
#2655
1"
b00000000000000000000000000000000 $
#2660
0"
b1010111010 #
#2665
1"
#2670
0"
b1011101110 #
#2675
1"
#2680
0"
b0000000000 #
#2685
1"
b00000000000000000000000010110111 $
#2690
0"
b0100111001 #
#2695
1"
b00000000000000000000000000000000 $
#2700
0"
b0000000001 #
#2705
1"
b00000000000000000000000000010000 $
#2710
0"
b1111111110 #
#2715
1"
b00000000000000000000000000000000 $
#2720
0"
b1010101011 #
#2725
1"
#2730
0"
b1010101110 #
#2735
1"
#2740
0"
b0000000000 #
#2745
1"
b00000000000000000000000010110111 $
#2750
0"
b1010110010 #
#2755
1"
b00000000000000000000000000000000 $
#2760
0"
b0001000000 #
#2765
1"
b00000000000000000000000000000001 $
#2770
0"
b1110111111 #
#2775
1"
b00000000000000000000000000000000 $
#2780
0"
b1011101010 #
#2785
1"
#2790
0"
b1110111010 #
#2795
1"
#2800
0"
b0000000000 #
#2805
1"
b00000000000000000000000010110111 $
#2810
0"
b1110101010 #
#2815
1"
b00000000000000000000000000000000 $
#2820
0"
b0000000100 #
#2825
1"
b00000000000000000000000010010011 $
#2830
0"
b1111111011 #
#2835
1"
b00000000000000000000000000000000 $
#2840
0"
b1010101110 #
#2845
1"
#2850
0"
b1010111011 #
#2855
1"
#2860
0"
b0000000000 #
#2865
1"
b00000000000000000000000010110111 $
#2870
0"
b1100001011 #
#2875
1"
b00000000000000000000000000000000 $
#2880
0"
b0100000000 #
#2885
1"
#2890
0"
b1011111111 #
#2895
1"
#2900
0"
b1110101010 #
#2905
1"
#2910
0"
b1011101010 #
#2915
1"
#2920
0"
b0000000000 #
#2925
1"
b00000000000000000000000010110111 $
#2930
0"
b1001110010 #
#2935
1"
b00000000000000000000000000000000 $
#2940
0"
b0000010000 #
#2945
1"
b00000000000000000000000010110111 $
#2950
0"
b1111101111 #
#2955
1"
b00000000000000000000000000000000 $
#2960
0"
b1010111010 #
#2965
1"
#2970
0"
b1011101110 #
#2975
1"
#2980
0"
b0000000000 #
#2985
1"
b00000000000000000000000010110111 $
#2990
0"
b1000110011 #
#2995
1"
b00000000000000000000000000000000 $
#3000
0"
b0000000001 #
#3005
1"
b00000000000000000000000000010000 $
#3010
0"
b1111111110 #
#3015
1"
b00000000000000000000000000000000 $
#3020
0"
b1010101011 #
#3025
1"
#3030
0"
b1010101110 #
#3035
1"
#3040
0"
b0000000000 #
#3045
1"
b00000000000000000000000010110111 $
#3050
0"
b0111000011 #
#3055
1"
b00000000000000000000000000000000 $
#3060
0"
b0001000000 #
#3065
1"
b00000000000000000000000000000001 $
#3070
0"
b1110111111 #
#3075
1"
b00000000000000000000000000000000 $
#3080
0"
b1011101010 #
#3085
1"
#3090
0"
b1110111010 #
#3095
1"
#3100
0"
b0000000000 #
#3105
1"
b00000000000000000000000010110111 $
#3110
0"
b0001001011 #
#3115
1"
b00000000000000000000000000000000 $
#3120
0"
b0000000100 #
#3125
1"
b00000000000000000000000010010011 $
#3130
0"
b1111111011 #
#3135
1"
b00000000000000000000000000000000 $
#3140
0"
b1010101110 #
#3145
1"
#3150
0"
b1010111011 #
#3155
1"
#3160
0"
b0000000000 #
#3165
1"
b00000000000000000000000010110111 $
#3170
0"
b1111010110 #
#3175
1"
b00000000000000000000000000000000 $
#3180
0"
b0100000000 #
#3185
1"
#3190
0"
b1011111111 #
#3195
1"
#3200
0"
b1110101010 #
#3205
1"
#3210
0"
b1011101010 #
#3215
1"
#3220
0"
b0000000000 #
#3225
1"
b00000000000000000000000010110111 $
#3230
0"
b0011101111 #
#3235
1"
b00000000000000000000000000000000 $
#3240
0"
b0000010000 #
#3245
1"
b00000000000000000000000010110111 $
#3250
0"
b1111101111 #
#3255
1"
b00000000000000000000000000000000 $
#3260
0"
b1010111010 #
#3265
1"
#3270
0"
b1011101110 #
#3275
1"
#3280
0"
b0000000000 #
#3285
1"
b00000000000000000000000010110111 $
#3290
0"
b0010001001 #
#3295
1"
b00000000000000000000000000000000 $
#3300
0"
b0000000001 #
#3305
1"
b00000000000000000000000000010000 $
#3310
0"
b1111111110 #
#3315
1"
b00000000000000000000000000000000 $
#3320
0"
b1010101011 #
#3325
1"
#3330
0"
b1010101110 #
#3335
1"
#3340
0"
b0000000000 #
#3345
1"
b00000000000000000000000010110111 $
#3350
0"
b1010100001 #
#3355
1"
b00000000000000000000000000000000 $
#3360
0"
b0001000000 #
#3365
1"
b00000000000000000000000000000001 $
#3370
0"
b1110111111 #
#3375
1"
b00000000000000000000000000000000 $
#3380
0"
b1011101010 #
#3385
1"
#3390
0"
b1110111010 #
#3395
1"
#3400
0"
b0000000000 #
#3405
1"
b00000000000000000000000010110111 $
#3410
0"
b0111111011 #
#3415
1"
b00000000000000000000000000000000 $
#3420
0"
b0000000100 #
#3425
1"
b00000000000000000000000010010011 $
#3430
0"
b1111111011 #
#3435
1"
b00000000000000000000000000000000 $
#3440
0"
b1010101110 #
#3445
1"
#3450
0"
b1010111011 #
#3455
1"
#3460
0"
b0000000000 #
#3465
1"
b00000000000000000000000010110111 $
#3470
0"
b1101101100 #
#3475
1"
b00000000000000000000000000000000 $
#3480
0"
b0100000000 #
#3485
1"
#3490
0"
b1011111111 #
#3495
1"
#3500
0"
b1110101010 #
#3505
1"
#3510
0"
b1011101010 #
#3515
1"
#3520
0"
b0000000000 #
#3525
1"
b00000000000000000000000010110111 $
#3530
0"
b1011110111 #
#3535
1"
b00000000000000000000000000000000 $
#3540
0"
b0000010000 #
#3545
1"
b00000000000000000000000010110111 $
#3550
0"
b1111101111 #
#3555
1"
b00000000000000000000000000000000 $
#3560
0"
b1010111010 #
#3565
1"
#3570
0"
b1011101110 #
#3575
1"
#3580
0"
b0000000000 #
#3585
1"
b00000000000000000000000010110111 $
#3590
0"
b0101111100 #
#3595
1"
b00000000000000000000000000000000 $
#3600
0"
b0000000001 #
#3605
1"
b00000000000000000000000000010000 $
#3610
0"
b1111111110 #
#3615
1"
b00000000000000000000000000000000 $
#3620
0"
b1010101011 #
#3625
1"
#3630
0"
b1010101110 #
#3635
1"
#3640
0"
b0000000000 #
#3645
1"
b00000000000000000000000010110111 $
#3650
0"
b1010110000 #
#3655
1"
b00000000000000000000000000000000 $
#3660
0"
b0001000000 #
#3665
1"
b00000000000000000000000000000001 $
#3670
0"
b1110111111 #
#3675
1"
b00000000000000000000000000000000 $
#3680
0"
b1011101010 #
#3685
1"
#3690
0"
b1110111010 #
#3695
1"
#3700
0"
b0000000000 #
#3705
1"
b00000000000000000000000010110111 $
#3710
0"
b0110000101 #
#3715
1"
b00000000000000000000000000000000 $
#3720
0"
b0000000100 #
#3725
1"
b00000000000000000000000010010011 $
#3730
0"
b1111111011 #
#3735
1"
b00000000000000000000000000000000 $
#3740
0"
b1010101110 #
#3745
1"
#3750
0"
b1010111011 #
#3755
1"
#3760
0"
b0000000000 #
#3765
1"
b00000000000000000000000010110111 $
#3770
0"
b0101000100 #
#3775
1"
b00000000000000000000000000000000 $
#3780
0"
b0100000000 #
#3785
1"
#3790
0"
b1011111111 #
#3795
1"
#3800
0"
b1110101010 #
#3805
1"
#3810
0"
b1011101010 #
#3815
1"
#3820
0"
b0000000000 #
#3825
1"
b00000000000000000000000010110111 $
#3830
0"
b1110001001 #
#3835
1"
b00000000000000000000000000000000 $
#3840
0"
b0000010000 #
#3845
1"
b00000000000000000000000010110111 $
#3850
0"
b1111101111 #
#3855
1"
b00000000000000000000000000000000 $
#3860
0"
b1010111010 #
#3865
1"
#3870
0"
b1011101110 #
#3875
1"
#3880
0"
b0000000000 #
#3885
1"
b00000000000000000000000010110111 $
#3890
0"
#3895
1"
#3900
0"
b0000000001 #
#3905
1"
b00000000000000000000000000010000 $
#3910
0"
b1111111110 #
#3915
1"
b00000000000000000000000000000000 $
#3920
0"
b1010101011 #
#3925
1"
#3930
0"
b1010101110 #
#3935
1"
#3940
0"
b0000000000 #
#3945
1"
b00000000000000000000000010110111 $
#3950
0"
b0001000111 #
#3955
1"
b00000000000000000000000000000000 $
#3960
0"
b0001000000 #
#3965
1"
b00000000000000000000000000000001 $
#3970
0"
b1110111111 #
#3975
1"
b00000000000000000000000000000000 $
#3980
0"
b1011101010 #
#3985
1"
#3990
0"
b1110111010 #
#3995
1"
#4000
0"
b0000000000 #
#4005
1"
b00000000000000000000000010110111 $
#4010
0"
b1011000011 #
#4015
1"
b00000000000000000000000000000000 $
#4020
0"
b0000000100 #
#4025
1"
b00000000000000000000000010010011 $
#4030
0"
b1111111011 #
#4035
1"
b00000000000000000000000000000000 $
#4040
0"
b1010101110 #
#4045
1"
#4050
0"
b1010111011 #
#4055
1"
#4060
0"
b0000000000 #
#4065
1"
b00000000000000000000000010110111 $
#4070
0"
b0001001011 #
#4075
1"
b00000000000000000000000000000000 $
#4080
0"
b0100000000 #
#4085
1"
#4090
0"
b1011111111 #
#4095
1"
#4100
0"
b1110101010 #
#4105
1"
#4110
0"
b1011101010 #
#4115
1"
#4120
0"
b0000000000 #
#4125
1"
b00000000000000000000000010110111 $
#4130
0"
b0100001011 #
#4135
1"
b00000000000000000000000000000000 $
#4140
0"
b0000010000 #
#4145
1"
b00000000000000000000000010110111 $
#4150
0"
b1111101111 #
#4155
1"
b00000000000000000000000000000000 $
#4160
0"
b1010111010 #
#4165
1"
#4170
0"
b1011101110 #
#4175
1"
#4180
0"
b0000000000 #
#4185
1"
b00000000000000000000000010110111 $
#4190
0"
b1011001100 #
#4195
1"
b00000000000000000000000000000000 $
#4200
0"
b0000000001 #
#4205
1"
b00000000000000000000000000010000 $
#4210
0"
b1111111110 #
#4215
1"
b00000000000000000000000000000000 $
#4220
0"
b1010101011 #
#4225
1"
#4230
0"
b1010101110 #
#4235
1"
#4240
0"
b0000000000 #
#4245
1"
b00000000000000000000000010110111 $
#4250
0"
b1000101110 #
#4255
1"
b00000000000000000000000000000000 $
#4260
0"
b0001000000 #
#4265
1"
b00000000000000000000000000000001 $
#4270
0"
b1110111111 #
#4275
1"
b00000000000000000000000000000000 $
#4280
0"
b1011101010 #
#4285
1"
#4290
0"
b1110111010 #
#4295
1"
#4300
0"
b0000000000 #
#4305
1"
b00000000000000000000000010110111 $
#4310
0"
b0111000111 #
#4315
1"
b00000000000000000000000000000000 $
#4320
0"
b0000000100 #
#4325
1"
b00000000000000000000000010010011 $
#4330
0"
b1111111011 #
#4335
1"
b00000000000000000000000000000000 $
#4340
0"
b1010101110 #
#4345
1"
#4350
0"
b1010111011 #
#4355
1"
#4360
0"
b0000000000 #
#4365
1"
b00000000000000000000000010110111 $
#4370
0"
b1011110000 #
#4375
1"
b00000000000000000000000000000000 $
#4380
0"
b0100000000 #
#4385
1"
#4390
0"
b1011111111 #
#4395
1"
#4400
0"
b1110101010 #
#4405
1"
#4410
0"
b1011101010 #
#4415
1"
#4420
0"
b0000000000 #
#4425
1"
b00000000000000000000000010110111 $
#4430
0"
b1101010010 #
#4435
1"
b00000000000000000000000000000000 $
#4440
0"
b0000010000 #
#4445
1"
b00000000000000000000000010110111 $
#4450
0"
b1111101111 #
#4455
1"
b00000000000000000000000000000000 $
#4460
0"
b1010111010 #
#4465
1"
#4470
0"
b1011101110 #
#4475
1"
#4480
0"
b0000000000 #
#4485
1"
b00000000000000000000000010110111 $
#4490
0"
b1010011100 #
#4495
1"
b00000000000000000000000000000000 $
#4500
0"
b0000000001 #
#4505
1"
b00000000000000000000000000010000 $
#4510
0"
b1111111110 #
#4515
1"
b00000000000000000000000000000000 $
#4520
0"
b1010101011 #
#4525
1"
#4530
0"
b1010101110 #
#4535
1"
#4540
0"
b0000000000 #
#4545
1"
b00000000000000000000000010110111 $
#4550
0"
b0000101001 #
#4555
1"
b00000000000000000000000001000011 $
#4560
0"
b0001000000 #
#4565
1"
b00000000000000000000000000000001 $
#4570
0"
b1110111111 #
#4575
1"
b00000000000000000000000000000000 $
#4580
0"
b1011101010 #
#4585
1"
#4590
0"
b1110111010 #
#4595
1"
#4600
0"
b0000000000 #
#4605
1"
b00000000000000000000000010110111 $
#4610
0"
b1000000100 #
#4615
1"
b00000000000000000000000000000000 $
#4620
0"
b0000000100 #
#4625
1"
b00000000000000000000000010010011 $
#4630
0"
b1111111011 #
#4635
1"
b00000000000000000000000000000000 $
#4640
0"
b1010101110 #
#4645
1"
#4650
0"
b1010111011 #
#4655
1"
#4660
0"
b0000000000 #
#4665
1"
b00000000000000000000000010110111 $
#4670
0"
b1001000110 #
#4675
1"
b00000000000000000000000000000000 $
#4680
0"
b0100000000 #
#4685
1"
#4690
0"
b1011111111 #
#4695
1"
